weather_cli/__init__.py
weather_cli/cli.py
puke3615_weather_cli-0.1.0.dist-info/METADATA
puke3615_weather_cli-0.1.0.dist-info/WHEEL
puke3615_weather_cli-0.1.0.dist-info/entry_points.txt
puke3615_weather_cli-0.1.0.dist-info/RECORD
